haidata/__init__.py
haidata/drop_cols.py
haidata/fix_colnames.py
haidata/fix_empty_cols.py
haidata/fix_empty_rows.py
haidata/fix_encode.py
haidata/fix_excess_stdev.py
haidata/haidatacfg.py
haidata/haidatautils.py
haidata/to_datetime.py
haidata/turn_to_int.py
haidata-0.0.7.dist-info/DESCRIPTION.rst
haidata-0.0.7.dist-info/METADATA
haidata-0.0.7.dist-info/RECORD
haidata-0.0.7.dist-info/WHEEL
haidata-0.0.7.dist-info/metadata.json
haidata-0.0.7.dist-info/top_level.txt
